{
    "archive_url": "https://api.github.com/repos/saltstack/salt-cloud/{archive_format}{/ref}",
    "assignees_url": "https://api.github.com/repos/saltstack/salt-cloud/assignees{/user}",
    "blobs_url": "https://api.github.com/repos/saltstack/salt-cloud/git/blobs{/sha}",
    "branches_url": "https://api.github.com/repos/saltstack/salt-cloud/branches{/branch}",
    "clone_url": "https://github.com/saltstack/salt-cloud.git",
    "collaborators_url": "https://api.github.com/repos/saltstack/salt-cloud/collaborators{/collaborator}",
    "comments_url": "https://api.github.com/repos/saltstack/salt-cloud/comments{/number}",
    "commits_url": "https://api.github.com/repos/saltstack/salt-cloud/commits{/sha}",
    "compare_url": "https://api.github.com/repos/saltstack/salt-cloud/compare/{base}...{head}",
    "contents_url": "https://api.github.com/repos/saltstack/salt-cloud/contents/{+path}",
    "contributors_url": "https://api.github.com/repos/saltstack/salt-cloud/contributors",
    "created_at": "2012-04-29T14:02:54Z",
    "default_branch": "develop",
    "description": "Deprecated repo; now in mainline Salt",
    "downloads_url": "https://api.github.com/repos/saltstack/salt-cloud/downloads",
    "events_url": "https://api.github.com/repos/saltstack/salt-cloud/events",
    "fork": false,
    "forks": 131,
    "forks_count": 131,
    "forks_url": "https://api.github.com/repos/saltstack/salt-cloud/forks",
    "full_name": "saltstack/salt-cloud",
    "git_commits_url": "https://api.github.com/repos/saltstack/salt-cloud/git/commits{/sha}",
    "git_refs_url": "https://api.github.com/repos/saltstack/salt-cloud/git/refs{/sha}",
    "git_tags_url": "https://api.github.com/repos/saltstack/salt-cloud/git/tags{/sha}",
    "git_url": "git://github.com/saltstack/salt-cloud.git",
    "has_downloads": true,
    "has_issues": true,
    "has_wiki": false,
    "homepage": "",
    "hooks_url": "https://api.github.com/repos/saltstack/salt-cloud/hooks",
    "html_url": "https://github.com/saltstack/salt-cloud",
    "id": 4174733,
    "issue_comment_url": "https://api.github.com/repos/saltstack/salt-cloud/issues/comments/{number}",
    "issue_events_url": "https://api.github.com/repos/saltstack/salt-cloud/issues/events{/number}",
    "issues_url": "https://api.github.com/repos/saltstack/salt-cloud/issues{/number}",
    "keys_url": "https://api.github.com/repos/saltstack/salt-cloud/keys{/key_id}",
    "labels_url": "https://api.github.com/repos/saltstack/salt-cloud/labels{/name}",
    "language": "Python",
    "languages_url": "https://api.github.com/repos/saltstack/salt-cloud/languages",
    "merges_url": "https://api.github.com/repos/saltstack/salt-cloud/merges",
    "milestones_url": "https://api.github.com/repos/saltstack/salt-cloud/milestones{/number}",
    "mirror_url": null,
    "name": "salt-cloud",
    "notifications_url": "https://api.github.com/repos/saltstack/salt-cloud/notifications{?since,all,participating}",
    "open_issues": 79,
    "open_issues_count": 79,
    "owner": {
        "avatar_url": "https://avatars.githubusercontent.com/u/1147473?",
        "events_url": "https://api.github.com/users/saltstack/events{/privacy}",
        "followers_url": "https://api.github.com/users/saltstack/followers",
        "following_url": "https://api.github.com/users/saltstack/following{/other_user}",
        "gists_url": "https://api.github.com/users/saltstack/gists{/gist_id}",
        "gravatar_id": "8e25be5fcc652c85b518a5755986615f",
        "html_url": "https://github.com/saltstack",
        "id": 1147473,
        "login": "saltstack",
        "organizations_url": "https://api.github.com/users/saltstack/orgs",
        "received_events_url": "https://api.github.com/users/saltstack/received_events",
        "repos_url": "https://api.github.com/users/saltstack/repos",
        "site_admin": false,
        "starred_url": "https://api.github.com/users/saltstack/starred{/owner}{/repo}",
        "subscriptions_url": "https://api.github.com/users/saltstack/subscriptions",
        "type": "Organization",
        "url": "https://api.github.com/users/saltstack"
    },
    "private": false,
    "pulls_url": "https://api.github.com/repos/saltstack/salt-cloud/pulls{/number}",
    "pushed_at": "2014-02-13T12:29:25Z",
    "releases_url": "https://api.github.com/repos/saltstack/salt-cloud/releases{/id}",
    "score": 1.0,
    "size": 5391,
    "ssh_url": "git@github.com:saltstack/salt-cloud.git",
    "stargazers_count": 194,
    "stargazers_url": "https://api.github.com/repos/saltstack/salt-cloud/stargazers",
    "statuses_url": "https://api.github.com/repos/saltstack/salt-cloud/statuses/{sha}",
    "subscribers_url": "https://api.github.com/repos/saltstack/salt-cloud/subscribers",
    "subscription_url": "https://api.github.com/repos/saltstack/salt-cloud/subscription",
    "svn_url": "https://github.com/saltstack/salt-cloud",
    "tags_url": "https://api.github.com/repos/saltstack/salt-cloud/tags",
    "teams_url": "https://api.github.com/repos/saltstack/salt-cloud/teams",
    "trees_url": "https://api.github.com/repos/saltstack/salt-cloud/git/trees{/sha}",
    "updated_at": "2014-05-04T19:37:46Z",
    "url": "https://api.github.com/repos/saltstack/salt-cloud",
    "watchers": 194,
    "watchers_count": 194
}