{
    "archive_url": "https://api.github.com/repos/jorgebastida/glue/{archive_format}{/ref}",
    "assignees_url": "https://api.github.com/repos/jorgebastida/glue/assignees{/user}",
    "blobs_url": "https://api.github.com/repos/jorgebastida/glue/git/blobs{/sha}",
    "branches_url": "https://api.github.com/repos/jorgebastida/glue/branches{/branch}",
    "clone_url": "https://github.com/jorgebastida/glue.git",
    "collaborators_url": "https://api.github.com/repos/jorgebastida/glue/collaborators{/collaborator}",
    "comments_url": "https://api.github.com/repos/jorgebastida/glue/comments{/number}",
    "commits_url": "https://api.github.com/repos/jorgebastida/glue/commits{/sha}",
    "compare_url": "https://api.github.com/repos/jorgebastida/glue/compare/{base}...{head}",
    "contents_url": "https://api.github.com/repos/jorgebastida/glue/contents/{+path}",
    "contributors_url": "https://api.github.com/repos/jorgebastida/glue/contributors",
    "created_at": "2012-01-01T18:22:31Z",
    "default_branch": "master",
    "description": "Glue is a simple command line tool to generate CSS sprites",
    "downloads_url": "https://api.github.com/repos/jorgebastida/glue/downloads",
    "events_url": "https://api.github.com/repos/jorgebastida/glue/events",
    "fork": false,
    "forks": 155,
    "forks_count": 155,
    "forks_url": "https://api.github.com/repos/jorgebastida/glue/forks",
    "full_name": "jorgebastida/glue",
    "git_commits_url": "https://api.github.com/repos/jorgebastida/glue/git/commits{/sha}",
    "git_refs_url": "https://api.github.com/repos/jorgebastida/glue/git/refs{/sha}",
    "git_tags_url": "https://api.github.com/repos/jorgebastida/glue/git/tags{/sha}",
    "git_url": "git://github.com/jorgebastida/glue.git",
    "has_downloads": true,
    "has_issues": true,
    "has_wiki": false,
    "homepage": "http://glue.readthedocs.org",
    "hooks_url": "https://api.github.com/repos/jorgebastida/glue/hooks",
    "html_url": "https://github.com/jorgebastida/glue",
    "id": 3083478,
    "issue_comment_url": "https://api.github.com/repos/jorgebastida/glue/issues/comments/{number}",
    "issue_events_url": "https://api.github.com/repos/jorgebastida/glue/issues/events{/number}",
    "issues_url": "https://api.github.com/repos/jorgebastida/glue/issues{/number}",
    "keys_url": "https://api.github.com/repos/jorgebastida/glue/keys{/key_id}",
    "labels_url": "https://api.github.com/repos/jorgebastida/glue/labels{/name}",
    "language": "Python",
    "languages_url": "https://api.github.com/repos/jorgebastida/glue/languages",
    "merges_url": "https://api.github.com/repos/jorgebastida/glue/merges",
    "milestones_url": "https://api.github.com/repos/jorgebastida/glue/milestones{/number}",
    "mirror_url": null,
    "name": "glue",
    "notifications_url": "https://api.github.com/repos/jorgebastida/glue/notifications{?since,all,participating}",
    "open_issues": 22,
    "open_issues_count": 22,
    "owner": {
        "avatar_url": "https://avatars.githubusercontent.com/u/159782?",
        "events_url": "https://api.github.com/users/jorgebastida/events{/privacy}",
        "followers_url": "https://api.github.com/users/jorgebastida/followers",
        "following_url": "https://api.github.com/users/jorgebastida/following{/other_user}",
        "gists_url": "https://api.github.com/users/jorgebastida/gists{/gist_id}",
        "gravatar_id": "367b9b756f2cbc761885dfcb3b089d6b",
        "html_url": "https://github.com/jorgebastida",
        "id": 159782,
        "login": "jorgebastida",
        "organizations_url": "https://api.github.com/users/jorgebastida/orgs",
        "received_events_url": "https://api.github.com/users/jorgebastida/received_events",
        "repos_url": "https://api.github.com/users/jorgebastida/repos",
        "site_admin": false,
        "starred_url": "https://api.github.com/users/jorgebastida/starred{/owner}{/repo}",
        "subscriptions_url": "https://api.github.com/users/jorgebastida/subscriptions",
        "type": "User",
        "url": "https://api.github.com/users/jorgebastida"
    },
    "private": false,
    "pulls_url": "https://api.github.com/repos/jorgebastida/glue/pulls{/number}",
    "pushed_at": "2014-04-21T09:37:39Z",
    "releases_url": "https://api.github.com/repos/jorgebastida/glue/releases{/id}",
    "score": 1.0,
    "size": 3206,
    "ssh_url": "git@github.com:jorgebastida/glue.git",
    "stargazers_count": 2145,
    "stargazers_url": "https://api.github.com/repos/jorgebastida/glue/stargazers",
    "statuses_url": "https://api.github.com/repos/jorgebastida/glue/statuses/{sha}",
    "subscribers_url": "https://api.github.com/repos/jorgebastida/glue/subscribers",
    "subscription_url": "https://api.github.com/repos/jorgebastida/glue/subscription",
    "svn_url": "https://github.com/jorgebastida/glue",
    "tags_url": "https://api.github.com/repos/jorgebastida/glue/tags",
    "teams_url": "https://api.github.com/repos/jorgebastida/glue/teams",
    "trees_url": "https://api.github.com/repos/jorgebastida/glue/git/trees{/sha}",
    "updated_at": "2014-05-06T11:54:07Z",
    "url": "https://api.github.com/repos/jorgebastida/glue",
    "watchers": 2145,
    "watchers_count": 2145
}