{
    "archive_url": "https://api.github.com/repos/ericflo/django-pagination/{archive_format}{/ref}",
    "assignees_url": "https://api.github.com/repos/ericflo/django-pagination/assignees{/user}",
    "blobs_url": "https://api.github.com/repos/ericflo/django-pagination/git/blobs{/sha}",
    "branches_url": "https://api.github.com/repos/ericflo/django-pagination/branches{/branch}",
    "clone_url": "https://github.com/ericflo/django-pagination.git",
    "collaborators_url": "https://api.github.com/repos/ericflo/django-pagination/collaborators{/collaborator}",
    "comments_url": "https://api.github.com/repos/ericflo/django-pagination/comments{/number}",
    "commits_url": "https://api.github.com/repos/ericflo/django-pagination/commits{/sha}",
    "compare_url": "https://api.github.com/repos/ericflo/django-pagination/compare/{base}...{head}",
    "contents_url": "https://api.github.com/repos/ericflo/django-pagination/contents/{+path}",
    "contributors_url": "https://api.github.com/repos/ericflo/django-pagination/contributors",
    "created_at": "2008-12-05T07:33:39Z",
    "default_branch": "master",
    "description": "A set of utilities for creating robust pagination tools throughout a django application.",
    "downloads_url": "https://api.github.com/repos/ericflo/django-pagination/downloads",
    "events_url": "https://api.github.com/repos/ericflo/django-pagination/events",
    "fork": false,
    "forks": 168,
    "forks_count": 168,
    "forks_url": "https://api.github.com/repos/ericflo/django-pagination/forks",
    "full_name": "ericflo/django-pagination",
    "git_commits_url": "https://api.github.com/repos/ericflo/django-pagination/git/commits{/sha}",
    "git_refs_url": "https://api.github.com/repos/ericflo/django-pagination/git/refs{/sha}",
    "git_tags_url": "https://api.github.com/repos/ericflo/django-pagination/git/tags{/sha}",
    "git_url": "git://github.com/ericflo/django-pagination.git",
    "has_downloads": true,
    "has_issues": true,
    "has_wiki": true,
    "homepage": "http://code.google.com/p/django-pagination/",
    "hooks_url": "https://api.github.com/repos/ericflo/django-pagination/hooks",
    "html_url": "https://github.com/ericflo/django-pagination",
    "id": 85424,
    "issue_comment_url": "https://api.github.com/repos/ericflo/django-pagination/issues/comments/{number}",
    "issue_events_url": "https://api.github.com/repos/ericflo/django-pagination/issues/events{/number}",
    "issues_url": "https://api.github.com/repos/ericflo/django-pagination/issues{/number}",
    "keys_url": "https://api.github.com/repos/ericflo/django-pagination/keys{/key_id}",
    "labels_url": "https://api.github.com/repos/ericflo/django-pagination/labels{/name}",
    "language": "Python",
    "languages_url": "https://api.github.com/repos/ericflo/django-pagination/languages",
    "merges_url": "https://api.github.com/repos/ericflo/django-pagination/merges",
    "milestones_url": "https://api.github.com/repos/ericflo/django-pagination/milestones{/number}",
    "mirror_url": null,
    "name": "django-pagination",
    "notifications_url": "https://api.github.com/repos/ericflo/django-pagination/notifications{?since,all,participating}",
    "open_issues": 38,
    "open_issues_count": 38,
    "owner": {
        "avatar_url": "https://avatars.githubusercontent.com/u/1228?",
        "events_url": "https://api.github.com/users/ericflo/events{/privacy}",
        "followers_url": "https://api.github.com/users/ericflo/followers",
        "following_url": "https://api.github.com/users/ericflo/following{/other_user}",
        "gists_url": "https://api.github.com/users/ericflo/gists{/gist_id}",
        "gravatar_id": "04d6b8e8d3c68899ac88eb8623392150",
        "html_url": "https://github.com/ericflo",
        "id": 1228,
        "login": "ericflo",
        "organizations_url": "https://api.github.com/users/ericflo/orgs",
        "received_events_url": "https://api.github.com/users/ericflo/received_events",
        "repos_url": "https://api.github.com/users/ericflo/repos",
        "site_admin": false,
        "starred_url": "https://api.github.com/users/ericflo/starred{/owner}{/repo}",
        "subscriptions_url": "https://api.github.com/users/ericflo/subscriptions",
        "type": "User",
        "url": "https://api.github.com/users/ericflo"
    },
    "private": false,
    "pulls_url": "https://api.github.com/repos/ericflo/django-pagination/pulls{/number}",
    "pushed_at": "2011-10-19T15:00:23Z",
    "releases_url": "https://api.github.com/repos/ericflo/django-pagination/releases{/id}",
    "score": 1.0,
    "size": 658,
    "ssh_url": "git@github.com:ericflo/django-pagination.git",
    "stargazers_count": 415,
    "stargazers_url": "https://api.github.com/repos/ericflo/django-pagination/stargazers",
    "statuses_url": "https://api.github.com/repos/ericflo/django-pagination/statuses/{sha}",
    "subscribers_url": "https://api.github.com/repos/ericflo/django-pagination/subscribers",
    "subscription_url": "https://api.github.com/repos/ericflo/django-pagination/subscription",
    "svn_url": "https://github.com/ericflo/django-pagination",
    "tags_url": "https://api.github.com/repos/ericflo/django-pagination/tags",
    "teams_url": "https://api.github.com/repos/ericflo/django-pagination/teams",
    "trees_url": "https://api.github.com/repos/ericflo/django-pagination/git/trees{/sha}",
    "updated_at": "2014-04-28T02:39:51Z",
    "url": "https://api.github.com/repos/ericflo/django-pagination",
    "watchers": 415,
    "watchers_count": 415
}