{
    "archive_url": "https://api.github.com/repos/dtcooper/python-fitparse/{archive_format}{/ref}",
    "assignees_url": "https://api.github.com/repos/dtcooper/python-fitparse/assignees{/user}",
    "blobs_url": "https://api.github.com/repos/dtcooper/python-fitparse/git/blobs{/sha}",
    "branches_url": "https://api.github.com/repos/dtcooper/python-fitparse/branches{/branch}",
    "clone_url": "https://github.com/dtcooper/python-fitparse.git",
    "collaborators_url": "https://api.github.com/repos/dtcooper/python-fitparse/collaborators{/collaborator}",
    "comments_url": "https://api.github.com/repos/dtcooper/python-fitparse/comments{/number}",
    "commits_url": "https://api.github.com/repos/dtcooper/python-fitparse/commits{/sha}",
    "compare_url": "https://api.github.com/repos/dtcooper/python-fitparse/compare/{base}...{head}",
    "contents_url": "https://api.github.com/repos/dtcooper/python-fitparse/contents/{+path}",
    "contributors_url": "https://api.github.com/repos/dtcooper/python-fitparse/contributors",
    "created_at": "2011-08-09T02:57:46Z",
    "default_branch": "master",
    "description": "Python library to parse ANT/Garmin .FIT files",
    "downloads_url": "https://api.github.com/repos/dtcooper/python-fitparse/downloads",
    "events_url": "https://api.github.com/repos/dtcooper/python-fitparse/events",
    "fork": false,
    "forks": 27,
    "forks_count": 27,
    "forks_url": "https://api.github.com/repos/dtcooper/python-fitparse/forks",
    "full_name": "dtcooper/python-fitparse",
    "git_commits_url": "https://api.github.com/repos/dtcooper/python-fitparse/git/commits{/sha}",
    "git_refs_url": "https://api.github.com/repos/dtcooper/python-fitparse/git/refs{/sha}",
    "git_tags_url": "https://api.github.com/repos/dtcooper/python-fitparse/git/tags{/sha}",
    "git_url": "git://github.com/dtcooper/python-fitparse.git",
    "has_downloads": true,
    "has_issues": true,
    "has_wiki": true,
    "homepage": "",
    "hooks_url": "https://api.github.com/repos/dtcooper/python-fitparse/hooks",
    "html_url": "https://github.com/dtcooper/python-fitparse",
    "id": 2177204,
    "issue_comment_url": "https://api.github.com/repos/dtcooper/python-fitparse/issues/comments/{number}",
    "issue_events_url": "https://api.github.com/repos/dtcooper/python-fitparse/issues/events{/number}",
    "issues_url": "https://api.github.com/repos/dtcooper/python-fitparse/issues{/number}",
    "keys_url": "https://api.github.com/repos/dtcooper/python-fitparse/keys{/key_id}",
    "labels_url": "https://api.github.com/repos/dtcooper/python-fitparse/labels{/name}",
    "language": "Python",
    "languages_url": "https://api.github.com/repos/dtcooper/python-fitparse/languages",
    "merges_url": "https://api.github.com/repos/dtcooper/python-fitparse/merges",
    "milestones_url": "https://api.github.com/repos/dtcooper/python-fitparse/milestones{/number}",
    "mirror_url": null,
    "name": "python-fitparse",
    "notifications_url": "https://api.github.com/repos/dtcooper/python-fitparse/notifications{?since,all,participating}",
    "open_issues": 8,
    "open_issues_count": 8,
    "owner": {
        "avatar_url": "https://avatars.githubusercontent.com/u/873944?",
        "events_url": "https://api.github.com/users/dtcooper/events{/privacy}",
        "followers_url": "https://api.github.com/users/dtcooper/followers",
        "following_url": "https://api.github.com/users/dtcooper/following{/other_user}",
        "gists_url": "https://api.github.com/users/dtcooper/gists{/gist_id}",
        "gravatar_id": "70d9e9f41e6f661950e4614e20c67e99",
        "html_url": "https://github.com/dtcooper",
        "id": 873944,
        "login": "dtcooper",
        "organizations_url": "https://api.github.com/users/dtcooper/orgs",
        "received_events_url": "https://api.github.com/users/dtcooper/received_events",
        "repos_url": "https://api.github.com/users/dtcooper/repos",
        "site_admin": false,
        "starred_url": "https://api.github.com/users/dtcooper/starred{/owner}{/repo}",
        "subscriptions_url": "https://api.github.com/users/dtcooper/subscriptions",
        "type": "User",
        "url": "https://api.github.com/users/dtcooper"
    },
    "private": false,
    "pulls_url": "https://api.github.com/repos/dtcooper/python-fitparse/pulls{/number}",
    "pushed_at": "2013-02-06T22:05:14Z",
    "releases_url": "https://api.github.com/repos/dtcooper/python-fitparse/releases{/id}",
    "score": 1.0,
    "size": 2639,
    "ssh_url": "git@github.com:dtcooper/python-fitparse.git",
    "stargazers_count": 59,
    "stargazers_url": "https://api.github.com/repos/dtcooper/python-fitparse/stargazers",
    "statuses_url": "https://api.github.com/repos/dtcooper/python-fitparse/statuses/{sha}",
    "subscribers_url": "https://api.github.com/repos/dtcooper/python-fitparse/subscribers",
    "subscription_url": "https://api.github.com/repos/dtcooper/python-fitparse/subscription",
    "svn_url": "https://github.com/dtcooper/python-fitparse",
    "tags_url": "https://api.github.com/repos/dtcooper/python-fitparse/tags",
    "teams_url": "https://api.github.com/repos/dtcooper/python-fitparse/teams",
    "trees_url": "https://api.github.com/repos/dtcooper/python-fitparse/git/trees{/sha}",
    "updated_at": "2014-01-13T09:49:51Z",
    "url": "https://api.github.com/repos/dtcooper/python-fitparse",
    "watchers": 59,
    "watchers_count": 59
}