{
    "archive_url": "https://api.github.com/repos/ttscoff/popclipextensions/{archive_format}{/ref}",
    "assignees_url": "https://api.github.com/repos/ttscoff/popclipextensions/assignees{/user}",
    "blobs_url": "https://api.github.com/repos/ttscoff/popclipextensions/git/blobs{/sha}",
    "branches_url": "https://api.github.com/repos/ttscoff/popclipextensions/branches{/branch}",
    "clone_url": "https://github.com/ttscoff/popclipextensions.git",
    "collaborators_url": "https://api.github.com/repos/ttscoff/popclipextensions/collaborators{/collaborator}",
    "comments_url": "https://api.github.com/repos/ttscoff/popclipextensions/comments{/number}",
    "commits_url": "https://api.github.com/repos/ttscoff/popclipextensions/commits{/sha}",
    "compare_url": "https://api.github.com/repos/ttscoff/popclipextensions/compare/{base}...{head}",
    "contents_url": "https://api.github.com/repos/ttscoff/popclipextensions/contents/{+path}",
    "contributors_url": "https://api.github.com/repos/ttscoff/popclipextensions/contributors",
    "created_at": "2012-11-28T19:09:51Z",
    "default_branch": "master",
    "description": "Brett's PopClip Extensions",
    "downloads_url": "https://api.github.com/repos/ttscoff/popclipextensions/downloads",
    "events_url": "https://api.github.com/repos/ttscoff/popclipextensions/events",
    "fork": false,
    "forks": 15,
    "forks_count": 15,
    "forks_url": "https://api.github.com/repos/ttscoff/popclipextensions/forks",
    "full_name": "ttscoff/popclipextensions",
    "git_commits_url": "https://api.github.com/repos/ttscoff/popclipextensions/git/commits{/sha}",
    "git_refs_url": "https://api.github.com/repos/ttscoff/popclipextensions/git/refs{/sha}",
    "git_tags_url": "https://api.github.com/repos/ttscoff/popclipextensions/git/tags{/sha}",
    "git_url": "git://github.com/ttscoff/popclipextensions.git",
    "has_downloads": true,
    "has_issues": true,
    "has_wiki": true,
    "homepage": null,
    "hooks_url": "https://api.github.com/repos/ttscoff/popclipextensions/hooks",
    "html_url": "https://github.com/ttscoff/popclipextensions",
    "id": 6907938,
    "issue_comment_url": "https://api.github.com/repos/ttscoff/popclipextensions/issues/comments/{number}",
    "issue_events_url": "https://api.github.com/repos/ttscoff/popclipextensions/issues/events{/number}",
    "issues_url": "https://api.github.com/repos/ttscoff/popclipextensions/issues{/number}",
    "keys_url": "https://api.github.com/repos/ttscoff/popclipextensions/keys{/key_id}",
    "labels_url": "https://api.github.com/repos/ttscoff/popclipextensions/labels{/name}",
    "language": "Python",
    "languages_url": "https://api.github.com/repos/ttscoff/popclipextensions/languages",
    "merges_url": "https://api.github.com/repos/ttscoff/popclipextensions/merges",
    "milestones_url": "https://api.github.com/repos/ttscoff/popclipextensions/milestones{/number}",
    "mirror_url": null,
    "name": "popclipextensions",
    "notifications_url": "https://api.github.com/repos/ttscoff/popclipextensions/notifications{?since,all,participating}",
    "open_issues": 0,
    "open_issues_count": 0,
    "owner": {
        "avatar_url": "https://avatars.githubusercontent.com/u/47833?",
        "events_url": "https://api.github.com/users/ttscoff/events{/privacy}",
        "followers_url": "https://api.github.com/users/ttscoff/followers",
        "following_url": "https://api.github.com/users/ttscoff/following{/other_user}",
        "gists_url": "https://api.github.com/users/ttscoff/gists{/gist_id}",
        "gravatar_id": "5fd63e67639747af45ecf8f3b8c47b06",
        "html_url": "https://github.com/ttscoff",
        "id": 47833,
        "login": "ttscoff",
        "organizations_url": "https://api.github.com/users/ttscoff/orgs",
        "received_events_url": "https://api.github.com/users/ttscoff/received_events",
        "repos_url": "https://api.github.com/users/ttscoff/repos",
        "site_admin": false,
        "starred_url": "https://api.github.com/users/ttscoff/starred{/owner}{/repo}",
        "subscriptions_url": "https://api.github.com/users/ttscoff/subscriptions",
        "type": "User",
        "url": "https://api.github.com/users/ttscoff"
    },
    "private": false,
    "pulls_url": "https://api.github.com/repos/ttscoff/popclipextensions/pulls{/number}",
    "pushed_at": "2014-04-11T03:51:55Z",
    "releases_url": "https://api.github.com/repos/ttscoff/popclipextensions/releases{/id}",
    "score": 1.0,
    "size": 472,
    "ssh_url": "git@github.com:ttscoff/popclipextensions.git",
    "stargazers_count": 97,
    "stargazers_url": "https://api.github.com/repos/ttscoff/popclipextensions/stargazers",
    "statuses_url": "https://api.github.com/repos/ttscoff/popclipextensions/statuses/{sha}",
    "subscribers_url": "https://api.github.com/repos/ttscoff/popclipextensions/subscribers",
    "subscription_url": "https://api.github.com/repos/ttscoff/popclipextensions/subscription",
    "svn_url": "https://github.com/ttscoff/popclipextensions",
    "tags_url": "https://api.github.com/repos/ttscoff/popclipextensions/tags",
    "teams_url": "https://api.github.com/repos/ttscoff/popclipextensions/teams",
    "trees_url": "https://api.github.com/repos/ttscoff/popclipextensions/git/trees{/sha}",
    "updated_at": "2014-05-05T08:06:46Z",
    "url": "https://api.github.com/repos/ttscoff/popclipextensions",
    "watchers": 97,
    "watchers_count": 97
}