{
    "archive_url": "https://api.github.com/repos/worldveil/dejavu/{archive_format}{/ref}",
    "assignees_url": "https://api.github.com/repos/worldveil/dejavu/assignees{/user}",
    "blobs_url": "https://api.github.com/repos/worldveil/dejavu/git/blobs{/sha}",
    "branches_url": "https://api.github.com/repos/worldveil/dejavu/branches{/branch}",
    "clone_url": "https://github.com/worldveil/dejavu.git",
    "collaborators_url": "https://api.github.com/repos/worldveil/dejavu/collaborators{/collaborator}",
    "comments_url": "https://api.github.com/repos/worldveil/dejavu/comments{/number}",
    "commits_url": "https://api.github.com/repos/worldveil/dejavu/commits{/sha}",
    "compare_url": "https://api.github.com/repos/worldveil/dejavu/compare/{base}...{head}",
    "contents_url": "https://api.github.com/repos/worldveil/dejavu/contents/{+path}",
    "contributors_url": "https://api.github.com/repos/worldveil/dejavu/contributors",
    "created_at": "2013-11-19T02:50:35Z",
    "default_branch": "master",
    "description": "Audio fingerprinting and recognition in Python",
    "downloads_url": "https://api.github.com/repos/worldveil/dejavu/downloads",
    "events_url": "https://api.github.com/repos/worldveil/dejavu/events",
    "fork": false,
    "forks": 53,
    "forks_count": 53,
    "forks_url": "https://api.github.com/repos/worldveil/dejavu/forks",
    "full_name": "worldveil/dejavu",
    "git_commits_url": "https://api.github.com/repos/worldveil/dejavu/git/commits{/sha}",
    "git_refs_url": "https://api.github.com/repos/worldveil/dejavu/git/refs{/sha}",
    "git_tags_url": "https://api.github.com/repos/worldveil/dejavu/git/tags{/sha}",
    "git_url": "git://github.com/worldveil/dejavu.git",
    "has_downloads": true,
    "has_issues": true,
    "has_wiki": true,
    "homepage": null,
    "hooks_url": "https://api.github.com/repos/worldveil/dejavu/hooks",
    "html_url": "https://github.com/worldveil/dejavu",
    "id": 14512299,
    "issue_comment_url": "https://api.github.com/repos/worldveil/dejavu/issues/comments/{number}",
    "issue_events_url": "https://api.github.com/repos/worldveil/dejavu/issues/events{/number}",
    "issues_url": "https://api.github.com/repos/worldveil/dejavu/issues{/number}",
    "keys_url": "https://api.github.com/repos/worldveil/dejavu/keys{/key_id}",
    "labels_url": "https://api.github.com/repos/worldveil/dejavu/labels{/name}",
    "language": "Python",
    "languages_url": "https://api.github.com/repos/worldveil/dejavu/languages",
    "merges_url": "https://api.github.com/repos/worldveil/dejavu/merges",
    "milestones_url": "https://api.github.com/repos/worldveil/dejavu/milestones{/number}",
    "mirror_url": null,
    "name": "dejavu",
    "notifications_url": "https://api.github.com/repos/worldveil/dejavu/notifications{?since,all,participating}",
    "open_issues": 4,
    "open_issues_count": 4,
    "owner": {
        "avatar_url": "https://avatars.githubusercontent.com/u/1045250?",
        "events_url": "https://api.github.com/users/worldveil/events{/privacy}",
        "followers_url": "https://api.github.com/users/worldveil/followers",
        "following_url": "https://api.github.com/users/worldveil/following{/other_user}",
        "gists_url": "https://api.github.com/users/worldveil/gists{/gist_id}",
        "gravatar_id": "c5ad6f27f1e7160f6fdb9618e333caa9",
        "html_url": "https://github.com/worldveil",
        "id": 1045250,
        "login": "worldveil",
        "organizations_url": "https://api.github.com/users/worldveil/orgs",
        "received_events_url": "https://api.github.com/users/worldveil/received_events",
        "repos_url": "https://api.github.com/users/worldveil/repos",
        "site_admin": false,
        "starred_url": "https://api.github.com/users/worldveil/starred{/owner}{/repo}",
        "subscriptions_url": "https://api.github.com/users/worldveil/subscriptions",
        "type": "User",
        "url": "https://api.github.com/users/worldveil"
    },
    "private": false,
    "pulls_url": "https://api.github.com/repos/worldveil/dejavu/pulls{/number}",
    "pushed_at": "2014-03-05T06:30:22Z",
    "releases_url": "https://api.github.com/repos/worldveil/dejavu/releases{/id}",
    "score": 1.0,
    "size": 2706,
    "ssh_url": "git@github.com:worldveil/dejavu.git",
    "stargazers_count": 509,
    "stargazers_url": "https://api.github.com/repos/worldveil/dejavu/stargazers",
    "statuses_url": "https://api.github.com/repos/worldveil/dejavu/statuses/{sha}",
    "subscribers_url": "https://api.github.com/repos/worldveil/dejavu/subscribers",
    "subscription_url": "https://api.github.com/repos/worldveil/dejavu/subscription",
    "svn_url": "https://github.com/worldveil/dejavu",
    "tags_url": "https://api.github.com/repos/worldveil/dejavu/tags",
    "teams_url": "https://api.github.com/repos/worldveil/dejavu/teams",
    "trees_url": "https://api.github.com/repos/worldveil/dejavu/git/trees{/sha}",
    "updated_at": "2014-05-07T01:48:38Z",
    "url": "https://api.github.com/repos/worldveil/dejavu",
    "watchers": 509,
    "watchers_count": 509
}