{
    "archive_url": "https://api.github.com/repos/akulakov/django/{archive_format}{/ref}",
    "assignees_url": "https://api.github.com/repos/akulakov/django/assignees{/user}",
    "blobs_url": "https://api.github.com/repos/akulakov/django/git/blobs{/sha}",
    "branches_url": "https://api.github.com/repos/akulakov/django/branches{/branch}",
    "clone_url": "https://github.com/akulakov/django.git",
    "collaborators_url": "https://api.github.com/repos/akulakov/django/collaborators{/collaborator}",
    "comments_url": "https://api.github.com/repos/akulakov/django/comments{/number}",
    "commits_url": "https://api.github.com/repos/akulakov/django/commits{/sha}",
    "compare_url": "https://api.github.com/repos/akulakov/django/compare/{base}...{head}",
    "contents_url": "https://api.github.com/repos/akulakov/django/contents/{+path}",
    "contributors_url": "https://api.github.com/repos/akulakov/django/contributors",
    "created_at": "2013-01-27T22:29:03Z",
    "default_branch": "master",
    "description": "",
    "downloads_url": "https://api.github.com/repos/akulakov/django/downloads",
    "events_url": "https://api.github.com/repos/akulakov/django/events",
    "fork": false,
    "forks": 101,
    "forks_count": 101,
    "forks_url": "https://api.github.com/repos/akulakov/django/forks",
    "full_name": "akulakov/django",
    "git_commits_url": "https://api.github.com/repos/akulakov/django/git/commits{/sha}",
    "git_refs_url": "https://api.github.com/repos/akulakov/django/git/refs{/sha}",
    "git_tags_url": "https://api.github.com/repos/akulakov/django/git/tags{/sha}",
    "git_url": "git://github.com/akulakov/django.git",
    "has_downloads": true,
    "has_issues": true,
    "has_wiki": true,
    "homepage": null,
    "hooks_url": "https://api.github.com/repos/akulakov/django/hooks",
    "html_url": "https://github.com/akulakov/django",
    "id": 7859079,
    "issue_comment_url": "https://api.github.com/repos/akulakov/django/issues/comments/{number}",
    "issue_events_url": "https://api.github.com/repos/akulakov/django/issues/events{/number}",
    "issues_url": "https://api.github.com/repos/akulakov/django/issues{/number}",
    "keys_url": "https://api.github.com/repos/akulakov/django/keys{/key_id}",
    "labels_url": "https://api.github.com/repos/akulakov/django/labels{/name}",
    "language": "Python",
    "languages_url": "https://api.github.com/repos/akulakov/django/languages",
    "merges_url": "https://api.github.com/repos/akulakov/django/merges",
    "milestones_url": "https://api.github.com/repos/akulakov/django/milestones{/number}",
    "mirror_url": null,
    "name": "django",
    "notifications_url": "https://api.github.com/repos/akulakov/django/notifications{?since,all,participating}",
    "open_issues": 1,
    "open_issues_count": 1,
    "owner": {
        "avatar_url": "https://avatars.githubusercontent.com/u/243874?",
        "events_url": "https://api.github.com/users/akulakov/events{/privacy}",
        "followers_url": "https://api.github.com/users/akulakov/followers",
        "following_url": "https://api.github.com/users/akulakov/following{/other_user}",
        "gists_url": "https://api.github.com/users/akulakov/gists{/gist_id}",
        "gravatar_id": "b205ae3e1e19c0f7661d66f92c00cad9",
        "html_url": "https://github.com/akulakov",
        "id": 243874,
        "login": "akulakov",
        "organizations_url": "https://api.github.com/users/akulakov/orgs",
        "received_events_url": "https://api.github.com/users/akulakov/received_events",
        "repos_url": "https://api.github.com/users/akulakov/repos",
        "site_admin": false,
        "starred_url": "https://api.github.com/users/akulakov/starred{/owner}{/repo}",
        "subscriptions_url": "https://api.github.com/users/akulakov/subscriptions",
        "type": "User",
        "url": "https://api.github.com/users/akulakov"
    },
    "private": false,
    "pulls_url": "https://api.github.com/repos/akulakov/django/pulls{/number}",
    "pushed_at": "2014-04-12T00:13:53Z",
    "releases_url": "https://api.github.com/repos/akulakov/django/releases{/id}",
    "score": 1.0,
    "size": 2175,
    "ssh_url": "git@github.com:akulakov/django.git",
    "stargazers_count": 58,
    "stargazers_url": "https://api.github.com/repos/akulakov/django/stargazers",
    "statuses_url": "https://api.github.com/repos/akulakov/django/statuses/{sha}",
    "subscribers_url": "https://api.github.com/repos/akulakov/django/subscribers",
    "subscription_url": "https://api.github.com/repos/akulakov/django/subscription",
    "svn_url": "https://github.com/akulakov/django",
    "tags_url": "https://api.github.com/repos/akulakov/django/tags",
    "teams_url": "https://api.github.com/repos/akulakov/django/teams",
    "trees_url": "https://api.github.com/repos/akulakov/django/git/trees{/sha}",
    "updated_at": "2014-04-27T17:20:42Z",
    "url": "https://api.github.com/repos/akulakov/django",
    "watchers": 58,
    "watchers_count": 58
}