{
    "archive_url": "https://api.github.com/repos/rafalp/Misago/{archive_format}{/ref}",
    "assignees_url": "https://api.github.com/repos/rafalp/Misago/assignees{/user}",
    "blobs_url": "https://api.github.com/repos/rafalp/Misago/git/blobs{/sha}",
    "branches_url": "https://api.github.com/repos/rafalp/Misago/branches{/branch}",
    "clone_url": "https://github.com/rafalp/Misago.git",
    "collaborators_url": "https://api.github.com/repos/rafalp/Misago/collaborators{/collaborator}",
    "comments_url": "https://api.github.com/repos/rafalp/Misago/comments{/number}",
    "commits_url": "https://api.github.com/repos/rafalp/Misago/commits{/sha}",
    "compare_url": "https://api.github.com/repos/rafalp/Misago/compare/{base}...{head}",
    "contents_url": "https://api.github.com/repos/rafalp/Misago/contents/{+path}",
    "contributors_url": "https://api.github.com/repos/rafalp/Misago/contributors",
    "created_at": "2012-06-22T14:24:02Z",
    "default_branch": "master",
    "description": "Misago is fully featured forum application standing on shoulders of Django.",
    "downloads_url": "https://api.github.com/repos/rafalp/Misago/downloads",
    "events_url": "https://api.github.com/repos/rafalp/Misago/events",
    "fork": false,
    "forks": 36,
    "forks_count": 36,
    "forks_url": "https://api.github.com/repos/rafalp/Misago/forks",
    "full_name": "rafalp/Misago",
    "git_commits_url": "https://api.github.com/repos/rafalp/Misago/git/commits{/sha}",
    "git_refs_url": "https://api.github.com/repos/rafalp/Misago/git/refs{/sha}",
    "git_tags_url": "https://api.github.com/repos/rafalp/Misago/git/tags{/sha}",
    "git_url": "git://github.com/rafalp/Misago.git",
    "has_downloads": true,
    "has_issues": true,
    "has_wiki": false,
    "homepage": "http://misago-project.org",
    "hooks_url": "https://api.github.com/repos/rafalp/Misago/hooks",
    "html_url": "https://github.com/rafalp/Misago",
    "id": 4751958,
    "issue_comment_url": "https://api.github.com/repos/rafalp/Misago/issues/comments/{number}",
    "issue_events_url": "https://api.github.com/repos/rafalp/Misago/issues/events{/number}",
    "issues_url": "https://api.github.com/repos/rafalp/Misago/issues{/number}",
    "keys_url": "https://api.github.com/repos/rafalp/Misago/keys{/key_id}",
    "labels_url": "https://api.github.com/repos/rafalp/Misago/labels{/name}",
    "language": "Python",
    "languages_url": "https://api.github.com/repos/rafalp/Misago/languages",
    "merges_url": "https://api.github.com/repos/rafalp/Misago/merges",
    "milestones_url": "https://api.github.com/repos/rafalp/Misago/milestones{/number}",
    "mirror_url": null,
    "name": "Misago",
    "notifications_url": "https://api.github.com/repos/rafalp/Misago/notifications{?since,all,participating}",
    "open_issues": 69,
    "open_issues_count": 69,
    "owner": {
        "avatar_url": "https://avatars.githubusercontent.com/u/750553?",
        "events_url": "https://api.github.com/users/rafalp/events{/privacy}",
        "followers_url": "https://api.github.com/users/rafalp/followers",
        "following_url": "https://api.github.com/users/rafalp/following{/other_user}",
        "gists_url": "https://api.github.com/users/rafalp/gists{/gist_id}",
        "gravatar_id": "15a051db3b90747d8f17848c17b2f3b9",
        "html_url": "https://github.com/rafalp",
        "id": 750553,
        "login": "rafalp",
        "organizations_url": "https://api.github.com/users/rafalp/orgs",
        "received_events_url": "https://api.github.com/users/rafalp/received_events",
        "repos_url": "https://api.github.com/users/rafalp/repos",
        "site_admin": false,
        "starred_url": "https://api.github.com/users/rafalp/starred{/owner}{/repo}",
        "subscriptions_url": "https://api.github.com/users/rafalp/subscriptions",
        "type": "User",
        "url": "https://api.github.com/users/rafalp"
    },
    "private": false,
    "pulls_url": "https://api.github.com/repos/rafalp/Misago/pulls{/number}",
    "pushed_at": "2014-05-06T22:34:49Z",
    "releases_url": "https://api.github.com/repos/rafalp/Misago/releases{/id}",
    "score": 1.0,
    "size": 12866,
    "ssh_url": "git@github.com:rafalp/Misago.git",
    "stargazers_count": 194,
    "stargazers_url": "https://api.github.com/repos/rafalp/Misago/stargazers",
    "statuses_url": "https://api.github.com/repos/rafalp/Misago/statuses/{sha}",
    "subscribers_url": "https://api.github.com/repos/rafalp/Misago/subscribers",
    "subscription_url": "https://api.github.com/repos/rafalp/Misago/subscription",
    "svn_url": "https://github.com/rafalp/Misago",
    "tags_url": "https://api.github.com/repos/rafalp/Misago/tags",
    "teams_url": "https://api.github.com/repos/rafalp/Misago/teams",
    "trees_url": "https://api.github.com/repos/rafalp/Misago/git/trees{/sha}",
    "updated_at": "2014-05-07T06:17:55Z",
    "url": "https://api.github.com/repos/rafalp/Misago",
    "watchers": 194,
    "watchers_count": 194
}