{
    "archive_url": "https://api.github.com/repos/halst/schema/{archive_format}{/ref}",
    "assignees_url": "https://api.github.com/repos/halst/schema/assignees{/user}",
    "blobs_url": "https://api.github.com/repos/halst/schema/git/blobs{/sha}",
    "branches_url": "https://api.github.com/repos/halst/schema/branches{/branch}",
    "clone_url": "https://github.com/halst/schema.git",
    "collaborators_url": "https://api.github.com/repos/halst/schema/collaborators{/collaborator}",
    "comments_url": "https://api.github.com/repos/halst/schema/comments{/number}",
    "commits_url": "https://api.github.com/repos/halst/schema/commits{/sha}",
    "compare_url": "https://api.github.com/repos/halst/schema/compare/{base}...{head}",
    "contents_url": "https://api.github.com/repos/halst/schema/contents/{+path}",
    "contributors_url": "https://api.github.com/repos/halst/schema/contributors",
    "created_at": "2012-08-19T18:56:20Z",
    "default_branch": "master",
    "description": "Schema validation just got Pythonic",
    "downloads_url": "https://api.github.com/repos/halst/schema/downloads",
    "events_url": "https://api.github.com/repos/halst/schema/events",
    "fork": false,
    "forks": 27,
    "forks_count": 27,
    "forks_url": "https://api.github.com/repos/halst/schema/forks",
    "full_name": "halst/schema",
    "git_commits_url": "https://api.github.com/repos/halst/schema/git/commits{/sha}",
    "git_refs_url": "https://api.github.com/repos/halst/schema/git/refs{/sha}",
    "git_tags_url": "https://api.github.com/repos/halst/schema/git/tags{/sha}",
    "git_url": "git://github.com/halst/schema.git",
    "has_downloads": true,
    "has_issues": true,
    "has_wiki": true,
    "homepage": "",
    "hooks_url": "https://api.github.com/repos/halst/schema/hooks",
    "html_url": "https://github.com/halst/schema",
    "id": 5473383,
    "issue_comment_url": "https://api.github.com/repos/halst/schema/issues/comments/{number}",
    "issue_events_url": "https://api.github.com/repos/halst/schema/issues/events{/number}",
    "issues_url": "https://api.github.com/repos/halst/schema/issues{/number}",
    "keys_url": "https://api.github.com/repos/halst/schema/keys{/key_id}",
    "labels_url": "https://api.github.com/repos/halst/schema/labels{/name}",
    "language": "Python",
    "languages_url": "https://api.github.com/repos/halst/schema/languages",
    "merges_url": "https://api.github.com/repos/halst/schema/merges",
    "milestones_url": "https://api.github.com/repos/halst/schema/milestones{/number}",
    "mirror_url": null,
    "name": "schema",
    "notifications_url": "https://api.github.com/repos/halst/schema/notifications{?since,all,participating}",
    "open_issues": 22,
    "open_issues_count": 22,
    "owner": {
        "avatar_url": "https://avatars.githubusercontent.com/u/619158?",
        "events_url": "https://api.github.com/users/halst/events{/privacy}",
        "followers_url": "https://api.github.com/users/halst/followers",
        "following_url": "https://api.github.com/users/halst/following{/other_user}",
        "gists_url": "https://api.github.com/users/halst/gists{/gist_id}",
        "gravatar_id": "8ae368318a55e95748b85f82ca83a289",
        "html_url": "https://github.com/halst",
        "id": 619158,
        "login": "halst",
        "organizations_url": "https://api.github.com/users/halst/orgs",
        "received_events_url": "https://api.github.com/users/halst/received_events",
        "repos_url": "https://api.github.com/users/halst/repos",
        "site_admin": false,
        "starred_url": "https://api.github.com/users/halst/starred{/owner}{/repo}",
        "subscriptions_url": "https://api.github.com/users/halst/subscriptions",
        "type": "User",
        "url": "https://api.github.com/users/halst"
    },
    "private": false,
    "pulls_url": "https://api.github.com/repos/halst/schema/pulls{/number}",
    "pushed_at": "2014-04-28T20:12:47Z",
    "releases_url": "https://api.github.com/repos/halst/schema/releases{/id}",
    "score": 1.0,
    "size": 574,
    "ssh_url": "git@github.com:halst/schema.git",
    "stargazers_count": 391,
    "stargazers_url": "https://api.github.com/repos/halst/schema/stargazers",
    "statuses_url": "https://api.github.com/repos/halst/schema/statuses/{sha}",
    "subscribers_url": "https://api.github.com/repos/halst/schema/subscribers",
    "subscription_url": "https://api.github.com/repos/halst/schema/subscription",
    "svn_url": "https://github.com/halst/schema",
    "tags_url": "https://api.github.com/repos/halst/schema/tags",
    "teams_url": "https://api.github.com/repos/halst/schema/teams",
    "trees_url": "https://api.github.com/repos/halst/schema/git/trees{/sha}",
    "updated_at": "2014-05-05T22:34:58Z",
    "url": "https://api.github.com/repos/halst/schema",
    "watchers": 391,
    "watchers_count": 391
}