{
    "archive_url": "https://api.github.com/repos/fperez/datarray/{archive_format}{/ref}",
    "assignees_url": "https://api.github.com/repos/fperez/datarray/assignees{/user}",
    "blobs_url": "https://api.github.com/repos/fperez/datarray/git/blobs{/sha}",
    "branches_url": "https://api.github.com/repos/fperez/datarray/branches{/branch}",
    "clone_url": "https://github.com/fperez/datarray.git",
    "collaborators_url": "https://api.github.com/repos/fperez/datarray/collaborators{/collaborator}",
    "comments_url": "https://api.github.com/repos/fperez/datarray/comments{/number}",
    "commits_url": "https://api.github.com/repos/fperez/datarray/commits{/sha}",
    "compare_url": "https://api.github.com/repos/fperez/datarray/compare/{base}...{head}",
    "contents_url": "https://api.github.com/repos/fperez/datarray/contents/{+path}",
    "contributors_url": "https://api.github.com/repos/fperez/datarray/contributors",
    "created_at": "2009-07-15T01:31:47Z",
    "default_branch": "master",
    "description": "Prototyping numpy arrays with named axes for data management. Docs are available at URL below",
    "downloads_url": "https://api.github.com/repos/fperez/datarray/downloads",
    "events_url": "https://api.github.com/repos/fperez/datarray/events",
    "fork": false,
    "forks": 22,
    "forks_count": 22,
    "forks_url": "https://api.github.com/repos/fperez/datarray/forks",
    "full_name": "fperez/datarray",
    "git_commits_url": "https://api.github.com/repos/fperez/datarray/git/commits{/sha}",
    "git_refs_url": "https://api.github.com/repos/fperez/datarray/git/refs{/sha}",
    "git_tags_url": "https://api.github.com/repos/fperez/datarray/git/tags{/sha}",
    "git_url": "git://github.com/fperez/datarray.git",
    "has_downloads": true,
    "has_issues": true,
    "has_wiki": true,
    "homepage": "http://fperez.github.com/datarray-doc",
    "hooks_url": "https://api.github.com/repos/fperez/datarray/hooks",
    "html_url": "https://github.com/fperez/datarray",
    "id": 251426,
    "issue_comment_url": "https://api.github.com/repos/fperez/datarray/issues/comments/{number}",
    "issue_events_url": "https://api.github.com/repos/fperez/datarray/issues/events{/number}",
    "issues_url": "https://api.github.com/repos/fperez/datarray/issues{/number}",
    "keys_url": "https://api.github.com/repos/fperez/datarray/keys{/key_id}",
    "labels_url": "https://api.github.com/repos/fperez/datarray/labels{/name}",
    "language": "Python",
    "languages_url": "https://api.github.com/repos/fperez/datarray/languages",
    "merges_url": "https://api.github.com/repos/fperez/datarray/merges",
    "milestones_url": "https://api.github.com/repos/fperez/datarray/milestones{/number}",
    "mirror_url": null,
    "name": "datarray",
    "notifications_url": "https://api.github.com/repos/fperez/datarray/notifications{?since,all,participating}",
    "open_issues": 11,
    "open_issues_count": 11,
    "owner": {
        "avatar_url": "https://avatars.githubusercontent.com/u/57394?",
        "events_url": "https://api.github.com/users/fperez/events{/privacy}",
        "followers_url": "https://api.github.com/users/fperez/followers",
        "following_url": "https://api.github.com/users/fperez/following{/other_user}",
        "gists_url": "https://api.github.com/users/fperez/gists{/gist_id}",
        "gravatar_id": "95198572b00e5fbcd97fb5315215bf7a",
        "html_url": "https://github.com/fperez",
        "id": 57394,
        "login": "fperez",
        "organizations_url": "https://api.github.com/users/fperez/orgs",
        "received_events_url": "https://api.github.com/users/fperez/received_events",
        "repos_url": "https://api.github.com/users/fperez/repos",
        "site_admin": false,
        "starred_url": "https://api.github.com/users/fperez/starred{/owner}{/repo}",
        "subscriptions_url": "https://api.github.com/users/fperez/subscriptions",
        "type": "User",
        "url": "https://api.github.com/users/fperez"
    },
    "private": false,
    "pulls_url": "https://api.github.com/repos/fperez/datarray/pulls{/number}",
    "pushed_at": "2011-11-19T01:39:38Z",
    "releases_url": "https://api.github.com/repos/fperez/datarray/releases{/id}",
    "score": 1.0,
    "size": 494,
    "ssh_url": "git@github.com:fperez/datarray.git",
    "stargazers_count": 48,
    "stargazers_url": "https://api.github.com/repos/fperez/datarray/stargazers",
    "statuses_url": "https://api.github.com/repos/fperez/datarray/statuses/{sha}",
    "subscribers_url": "https://api.github.com/repos/fperez/datarray/subscribers",
    "subscription_url": "https://api.github.com/repos/fperez/datarray/subscription",
    "svn_url": "https://github.com/fperez/datarray",
    "tags_url": "https://api.github.com/repos/fperez/datarray/tags",
    "teams_url": "https://api.github.com/repos/fperez/datarray/teams",
    "trees_url": "https://api.github.com/repos/fperez/datarray/git/trees{/sha}",
    "updated_at": "2013-10-31T13:43:02Z",
    "url": "https://api.github.com/repos/fperez/datarray",
    "watchers": 48,
    "watchers_count": 48
}