{
    "archive_url": "https://api.github.com/repos/tavendo/WAMP/{archive_format}{/ref}",
    "assignees_url": "https://api.github.com/repos/tavendo/WAMP/assignees{/user}",
    "blobs_url": "https://api.github.com/repos/tavendo/WAMP/git/blobs{/sha}",
    "branches_url": "https://api.github.com/repos/tavendo/WAMP/branches{/branch}",
    "clone_url": "https://github.com/tavendo/WAMP.git",
    "collaborators_url": "https://api.github.com/repos/tavendo/WAMP/collaborators{/collaborator}",
    "comments_url": "https://api.github.com/repos/tavendo/WAMP/comments{/number}",
    "commits_url": "https://api.github.com/repos/tavendo/WAMP/commits{/sha}",
    "compare_url": "https://api.github.com/repos/tavendo/WAMP/compare/{base}...{head}",
    "contents_url": "https://api.github.com/repos/tavendo/WAMP/contents/{+path}",
    "contributors_url": "https://api.github.com/repos/tavendo/WAMP/contributors",
    "created_at": "2012-03-23T16:27:22Z",
    "default_branch": "master",
    "description": "WAMP - The WebSocket Application Messaging Protocol",
    "downloads_url": "https://api.github.com/repos/tavendo/WAMP/downloads",
    "events_url": "https://api.github.com/repos/tavendo/WAMP/events",
    "fork": false,
    "forks": 10,
    "forks_count": 10,
    "forks_url": "https://api.github.com/repos/tavendo/WAMP/forks",
    "full_name": "tavendo/WAMP",
    "git_commits_url": "https://api.github.com/repos/tavendo/WAMP/git/commits{/sha}",
    "git_refs_url": "https://api.github.com/repos/tavendo/WAMP/git/refs{/sha}",
    "git_tags_url": "https://api.github.com/repos/tavendo/WAMP/git/tags{/sha}",
    "git_url": "git://github.com/tavendo/WAMP.git",
    "has_downloads": true,
    "has_issues": true,
    "has_wiki": true,
    "homepage": "http://wamp.ws",
    "hooks_url": "https://api.github.com/repos/tavendo/WAMP/hooks",
    "html_url": "https://github.com/tavendo/WAMP",
    "id": 3810228,
    "issue_comment_url": "https://api.github.com/repos/tavendo/WAMP/issues/comments/{number}",
    "issue_events_url": "https://api.github.com/repos/tavendo/WAMP/issues/events{/number}",
    "issues_url": "https://api.github.com/repos/tavendo/WAMP/issues{/number}",
    "keys_url": "https://api.github.com/repos/tavendo/WAMP/keys{/key_id}",
    "labels_url": "https://api.github.com/repos/tavendo/WAMP/labels{/name}",
    "language": "Python",
    "languages_url": "https://api.github.com/repos/tavendo/WAMP/languages",
    "merges_url": "https://api.github.com/repos/tavendo/WAMP/merges",
    "milestones_url": "https://api.github.com/repos/tavendo/WAMP/milestones{/number}",
    "mirror_url": null,
    "name": "WAMP",
    "notifications_url": "https://api.github.com/repos/tavendo/WAMP/notifications{?since,all,participating}",
    "open_issues": 18,
    "open_issues_count": 18,
    "owner": {
        "avatar_url": "https://avatars.githubusercontent.com/u/1519673?",
        "events_url": "https://api.github.com/users/tavendo/events{/privacy}",
        "followers_url": "https://api.github.com/users/tavendo/followers",
        "following_url": "https://api.github.com/users/tavendo/following{/other_user}",
        "gists_url": "https://api.github.com/users/tavendo/gists{/gist_id}",
        "gravatar_id": "2dec02e7ca30244cdeae9764223ba431",
        "html_url": "https://github.com/tavendo",
        "id": 1519673,
        "login": "tavendo",
        "organizations_url": "https://api.github.com/users/tavendo/orgs",
        "received_events_url": "https://api.github.com/users/tavendo/received_events",
        "repos_url": "https://api.github.com/users/tavendo/repos",
        "site_admin": false,
        "starred_url": "https://api.github.com/users/tavendo/starred{/owner}{/repo}",
        "subscriptions_url": "https://api.github.com/users/tavendo/subscriptions",
        "type": "Organization",
        "url": "https://api.github.com/users/tavendo"
    },
    "private": false,
    "pulls_url": "https://api.github.com/repos/tavendo/WAMP/pulls{/number}",
    "pushed_at": "2014-04-25T17:16:31Z",
    "releases_url": "https://api.github.com/repos/tavendo/WAMP/releases{/id}",
    "score": 1.0,
    "size": 4549,
    "ssh_url": "git@github.com:tavendo/WAMP.git",
    "stargazers_count": 46,
    "stargazers_url": "https://api.github.com/repos/tavendo/WAMP/stargazers",
    "statuses_url": "https://api.github.com/repos/tavendo/WAMP/statuses/{sha}",
    "subscribers_url": "https://api.github.com/repos/tavendo/WAMP/subscribers",
    "subscription_url": "https://api.github.com/repos/tavendo/WAMP/subscription",
    "svn_url": "https://github.com/tavendo/WAMP",
    "tags_url": "https://api.github.com/repos/tavendo/WAMP/tags",
    "teams_url": "https://api.github.com/repos/tavendo/WAMP/teams",
    "trees_url": "https://api.github.com/repos/tavendo/WAMP/git/trees{/sha}",
    "updated_at": "2014-05-06T16:25:17Z",
    "url": "https://api.github.com/repos/tavendo/WAMP",
    "watchers": 46,
    "watchers_count": 46
}