{
    "archive_url": "https://api.github.com/repos/patcoll/paypal-python/{archive_format}{/ref}",
    "assignees_url": "https://api.github.com/repos/patcoll/paypal-python/assignees{/user}",
    "blobs_url": "https://api.github.com/repos/patcoll/paypal-python/git/blobs{/sha}",
    "branches_url": "https://api.github.com/repos/patcoll/paypal-python/branches{/branch}",
    "clone_url": "https://github.com/patcoll/paypal-python.git",
    "collaborators_url": "https://api.github.com/repos/patcoll/paypal-python/collaborators{/collaborator}",
    "comments_url": "https://api.github.com/repos/patcoll/paypal-python/comments{/number}",
    "commits_url": "https://api.github.com/repos/patcoll/paypal-python/commits{/sha}",
    "compare_url": "https://api.github.com/repos/patcoll/paypal-python/compare/{base}...{head}",
    "contents_url": "https://api.github.com/repos/patcoll/paypal-python/contents/{+path}",
    "contributors_url": "https://api.github.com/repos/patcoll/paypal-python/contributors",
    "created_at": "2009-11-06T22:03:29Z",
    "default_branch": "master",
    "description": "Implementation of PayPal APIs in Python--canonical repository is at duointeractive/paypal-python",
    "downloads_url": "https://api.github.com/repos/patcoll/paypal-python/downloads",
    "events_url": "https://api.github.com/repos/patcoll/paypal-python/events",
    "fork": false,
    "forks": 27,
    "forks_count": 27,
    "forks_url": "https://api.github.com/repos/patcoll/paypal-python/forks",
    "full_name": "patcoll/paypal-python",
    "git_commits_url": "https://api.github.com/repos/patcoll/paypal-python/git/commits{/sha}",
    "git_refs_url": "https://api.github.com/repos/patcoll/paypal-python/git/refs{/sha}",
    "git_tags_url": "https://api.github.com/repos/patcoll/paypal-python/git/tags{/sha}",
    "git_url": "git://github.com/patcoll/paypal-python.git",
    "has_downloads": true,
    "has_issues": true,
    "has_wiki": true,
    "homepage": "http://github.com/duointeractive/paypal-python",
    "hooks_url": "https://api.github.com/repos/patcoll/paypal-python/hooks",
    "html_url": "https://github.com/patcoll/paypal-python",
    "id": 363827,
    "issue_comment_url": "https://api.github.com/repos/patcoll/paypal-python/issues/comments/{number}",
    "issue_events_url": "https://api.github.com/repos/patcoll/paypal-python/issues/events{/number}",
    "issues_url": "https://api.github.com/repos/patcoll/paypal-python/issues{/number}",
    "keys_url": "https://api.github.com/repos/patcoll/paypal-python/keys{/key_id}",
    "labels_url": "https://api.github.com/repos/patcoll/paypal-python/labels{/name}",
    "language": "Python",
    "languages_url": "https://api.github.com/repos/patcoll/paypal-python/languages",
    "merges_url": "https://api.github.com/repos/patcoll/paypal-python/merges",
    "milestones_url": "https://api.github.com/repos/patcoll/paypal-python/milestones{/number}",
    "mirror_url": null,
    "name": "paypal-python",
    "notifications_url": "https://api.github.com/repos/patcoll/paypal-python/notifications{?since,all,participating}",
    "open_issues": 1,
    "open_issues_count": 1,
    "owner": {
        "avatar_url": "https://avatars.githubusercontent.com/u/81328?",
        "events_url": "https://api.github.com/users/patcoll/events{/privacy}",
        "followers_url": "https://api.github.com/users/patcoll/followers",
        "following_url": "https://api.github.com/users/patcoll/following{/other_user}",
        "gists_url": "https://api.github.com/users/patcoll/gists{/gist_id}",
        "gravatar_id": "b289671dac2a82c40d00afbd17334aca",
        "html_url": "https://github.com/patcoll",
        "id": 81328,
        "login": "patcoll",
        "organizations_url": "https://api.github.com/users/patcoll/orgs",
        "received_events_url": "https://api.github.com/users/patcoll/received_events",
        "repos_url": "https://api.github.com/users/patcoll/repos",
        "site_admin": false,
        "starred_url": "https://api.github.com/users/patcoll/starred{/owner}{/repo}",
        "subscriptions_url": "https://api.github.com/users/patcoll/subscriptions",
        "type": "User",
        "url": "https://api.github.com/users/patcoll"
    },
    "private": false,
    "pulls_url": "https://api.github.com/repos/patcoll/paypal-python/pulls{/number}",
    "pushed_at": "2010-08-11T01:36:37Z",
    "releases_url": "https://api.github.com/repos/patcoll/paypal-python/releases{/id}",
    "score": 1.0,
    "size": 101,
    "ssh_url": "git@github.com:patcoll/paypal-python.git",
    "stargazers_count": 59,
    "stargazers_url": "https://api.github.com/repos/patcoll/paypal-python/stargazers",
    "statuses_url": "https://api.github.com/repos/patcoll/paypal-python/statuses/{sha}",
    "subscribers_url": "https://api.github.com/repos/patcoll/paypal-python/subscribers",
    "subscription_url": "https://api.github.com/repos/patcoll/paypal-python/subscription",
    "svn_url": "https://github.com/patcoll/paypal-python",
    "tags_url": "https://api.github.com/repos/patcoll/paypal-python/tags",
    "teams_url": "https://api.github.com/repos/patcoll/paypal-python/teams",
    "trees_url": "https://api.github.com/repos/patcoll/paypal-python/git/trees{/sha}",
    "updated_at": "2014-03-03T03:15:36Z",
    "url": "https://api.github.com/repos/patcoll/paypal-python",
    "watchers": 59,
    "watchers_count": 59
}