{
    "archive_url": "https://api.github.com/repos/benhamner/Metrics/{archive_format}{/ref}",
    "assignees_url": "https://api.github.com/repos/benhamner/Metrics/assignees{/user}",
    "blobs_url": "https://api.github.com/repos/benhamner/Metrics/git/blobs{/sha}",
    "branches_url": "https://api.github.com/repos/benhamner/Metrics/branches{/branch}",
    "clone_url": "https://github.com/benhamner/Metrics.git",
    "collaborators_url": "https://api.github.com/repos/benhamner/Metrics/collaborators{/collaborator}",
    "comments_url": "https://api.github.com/repos/benhamner/Metrics/comments{/number}",
    "commits_url": "https://api.github.com/repos/benhamner/Metrics/commits{/sha}",
    "compare_url": "https://api.github.com/repos/benhamner/Metrics/compare/{base}...{head}",
    "contents_url": "https://api.github.com/repos/benhamner/Metrics/contents/{+path}",
    "contributors_url": "https://api.github.com/repos/benhamner/Metrics/contributors",
    "created_at": "2012-06-12T15:52:50Z",
    "default_branch": "master",
    "description": "Machine learning evaluation metrics, implemented in Python, R, Haskell, and MATLAB / Octave",
    "downloads_url": "https://api.github.com/repos/benhamner/Metrics/downloads",
    "events_url": "https://api.github.com/repos/benhamner/Metrics/events",
    "fork": false,
    "forks": 32,
    "forks_count": 32,
    "forks_url": "https://api.github.com/repos/benhamner/Metrics/forks",
    "full_name": "benhamner/Metrics",
    "git_commits_url": "https://api.github.com/repos/benhamner/Metrics/git/commits{/sha}",
    "git_refs_url": "https://api.github.com/repos/benhamner/Metrics/git/refs{/sha}",
    "git_tags_url": "https://api.github.com/repos/benhamner/Metrics/git/tags{/sha}",
    "git_url": "git://github.com/benhamner/Metrics.git",
    "has_downloads": true,
    "has_issues": true,
    "has_wiki": true,
    "homepage": "",
    "hooks_url": "https://api.github.com/repos/benhamner/Metrics/hooks",
    "html_url": "https://github.com/benhamner/Metrics",
    "id": 4639444,
    "issue_comment_url": "https://api.github.com/repos/benhamner/Metrics/issues/comments/{number}",
    "issue_events_url": "https://api.github.com/repos/benhamner/Metrics/issues/events{/number}",
    "issues_url": "https://api.github.com/repos/benhamner/Metrics/issues{/number}",
    "keys_url": "https://api.github.com/repos/benhamner/Metrics/keys{/key_id}",
    "labels_url": "https://api.github.com/repos/benhamner/Metrics/labels{/name}",
    "language": "Python",
    "languages_url": "https://api.github.com/repos/benhamner/Metrics/languages",
    "merges_url": "https://api.github.com/repos/benhamner/Metrics/merges",
    "milestones_url": "https://api.github.com/repos/benhamner/Metrics/milestones{/number}",
    "mirror_url": null,
    "name": "Metrics",
    "notifications_url": "https://api.github.com/repos/benhamner/Metrics/notifications{?since,all,participating}",
    "open_issues": 2,
    "open_issues_count": 2,
    "owner": {
        "avatar_url": "https://avatars.githubusercontent.com/u/582878?",
        "events_url": "https://api.github.com/users/benhamner/events{/privacy}",
        "followers_url": "https://api.github.com/users/benhamner/followers",
        "following_url": "https://api.github.com/users/benhamner/following{/other_user}",
        "gists_url": "https://api.github.com/users/benhamner/gists{/gist_id}",
        "gravatar_id": "3b1e0cb8a09358a9d173d03b5261d116",
        "html_url": "https://github.com/benhamner",
        "id": 582878,
        "login": "benhamner",
        "organizations_url": "https://api.github.com/users/benhamner/orgs",
        "received_events_url": "https://api.github.com/users/benhamner/received_events",
        "repos_url": "https://api.github.com/users/benhamner/repos",
        "site_admin": false,
        "starred_url": "https://api.github.com/users/benhamner/starred{/owner}{/repo}",
        "subscriptions_url": "https://api.github.com/users/benhamner/subscriptions",
        "type": "User",
        "url": "https://api.github.com/users/benhamner"
    },
    "private": false,
    "pulls_url": "https://api.github.com/repos/benhamner/Metrics/pulls{/number}",
    "pushed_at": "2013-08-19T17:11:02Z",
    "releases_url": "https://api.github.com/repos/benhamner/Metrics/releases{/id}",
    "score": 1.0,
    "size": 440,
    "ssh_url": "git@github.com:benhamner/Metrics.git",
    "stargazers_count": 156,
    "stargazers_url": "https://api.github.com/repos/benhamner/Metrics/stargazers",
    "statuses_url": "https://api.github.com/repos/benhamner/Metrics/statuses/{sha}",
    "subscribers_url": "https://api.github.com/repos/benhamner/Metrics/subscribers",
    "subscription_url": "https://api.github.com/repos/benhamner/Metrics/subscription",
    "svn_url": "https://github.com/benhamner/Metrics",
    "tags_url": "https://api.github.com/repos/benhamner/Metrics/tags",
    "teams_url": "https://api.github.com/repos/benhamner/Metrics/teams",
    "trees_url": "https://api.github.com/repos/benhamner/Metrics/git/trees{/sha}",
    "updated_at": "2014-04-29T15:46:01Z",
    "url": "https://api.github.com/repos/benhamner/Metrics",
    "watchers": 156,
    "watchers_count": 156
}