{
    "archive_url": "https://api.github.com/repos/rfk/pyenchant/{archive_format}{/ref}",
    "assignees_url": "https://api.github.com/repos/rfk/pyenchant/assignees{/user}",
    "blobs_url": "https://api.github.com/repos/rfk/pyenchant/git/blobs{/sha}",
    "branches_url": "https://api.github.com/repos/rfk/pyenchant/branches{/branch}",
    "clone_url": "https://github.com/rfk/pyenchant.git",
    "collaborators_url": "https://api.github.com/repos/rfk/pyenchant/collaborators{/collaborator}",
    "comments_url": "https://api.github.com/repos/rfk/pyenchant/comments{/number}",
    "commits_url": "https://api.github.com/repos/rfk/pyenchant/commits{/sha}",
    "compare_url": "https://api.github.com/repos/rfk/pyenchant/compare/{base}...{head}",
    "contents_url": "https://api.github.com/repos/rfk/pyenchant/contents/{+path}",
    "contributors_url": "https://api.github.com/repos/rfk/pyenchant/contributors",
    "created_at": "2008-11-22T11:54:59Z",
    "default_branch": "master",
    "description": "spellchecking library for python",
    "downloads_url": "https://api.github.com/repos/rfk/pyenchant/downloads",
    "events_url": "https://api.github.com/repos/rfk/pyenchant/events",
    "fork": false,
    "forks": 12,
    "forks_count": 12,
    "forks_url": "https://api.github.com/repos/rfk/pyenchant/forks",
    "full_name": "rfk/pyenchant",
    "git_commits_url": "https://api.github.com/repos/rfk/pyenchant/git/commits{/sha}",
    "git_refs_url": "https://api.github.com/repos/rfk/pyenchant/git/refs{/sha}",
    "git_tags_url": "https://api.github.com/repos/rfk/pyenchant/git/tags{/sha}",
    "git_url": "git://github.com/rfk/pyenchant.git",
    "has_downloads": true,
    "has_issues": true,
    "has_wiki": true,
    "homepage": "http://www.rfk.id.au/software/pyenchant/",
    "hooks_url": "https://api.github.com/repos/rfk/pyenchant/hooks",
    "html_url": "https://github.com/rfk/pyenchant",
    "id": 79458,
    "issue_comment_url": "https://api.github.com/repos/rfk/pyenchant/issues/comments/{number}",
    "issue_events_url": "https://api.github.com/repos/rfk/pyenchant/issues/events{/number}",
    "issues_url": "https://api.github.com/repos/rfk/pyenchant/issues{/number}",
    "keys_url": "https://api.github.com/repos/rfk/pyenchant/keys{/key_id}",
    "labels_url": "https://api.github.com/repos/rfk/pyenchant/labels{/name}",
    "language": "Python",
    "languages_url": "https://api.github.com/repos/rfk/pyenchant/languages",
    "merges_url": "https://api.github.com/repos/rfk/pyenchant/merges",
    "milestones_url": "https://api.github.com/repos/rfk/pyenchant/milestones{/number}",
    "mirror_url": null,
    "name": "pyenchant",
    "notifications_url": "https://api.github.com/repos/rfk/pyenchant/notifications{?since,all,participating}",
    "open_issues": 13,
    "open_issues_count": 13,
    "owner": {
        "avatar_url": "https://avatars.githubusercontent.com/u/34695?",
        "events_url": "https://api.github.com/users/rfk/events{/privacy}",
        "followers_url": "https://api.github.com/users/rfk/followers",
        "following_url": "https://api.github.com/users/rfk/following{/other_user}",
        "gists_url": "https://api.github.com/users/rfk/gists{/gist_id}",
        "gravatar_id": "7ad57e27678b3a70d05e9c3fb1af123e",
        "html_url": "https://github.com/rfk",
        "id": 34695,
        "login": "rfk",
        "organizations_url": "https://api.github.com/users/rfk/orgs",
        "received_events_url": "https://api.github.com/users/rfk/received_events",
        "repos_url": "https://api.github.com/users/rfk/repos",
        "site_admin": false,
        "starred_url": "https://api.github.com/users/rfk/starred{/owner}{/repo}",
        "subscriptions_url": "https://api.github.com/users/rfk/subscriptions",
        "type": "User",
        "url": "https://api.github.com/users/rfk"
    },
    "private": false,
    "pulls_url": "https://api.github.com/repos/rfk/pyenchant/pulls{/number}",
    "pushed_at": "2014-04-29T04:59:58Z",
    "releases_url": "https://api.github.com/repos/rfk/pyenchant/releases{/id}",
    "score": 1.0,
    "size": 43413,
    "ssh_url": "git@github.com:rfk/pyenchant.git",
    "stargazers_count": 54,
    "stargazers_url": "https://api.github.com/repos/rfk/pyenchant/stargazers",
    "statuses_url": "https://api.github.com/repos/rfk/pyenchant/statuses/{sha}",
    "subscribers_url": "https://api.github.com/repos/rfk/pyenchant/subscribers",
    "subscription_url": "https://api.github.com/repos/rfk/pyenchant/subscription",
    "svn_url": "https://github.com/rfk/pyenchant",
    "tags_url": "https://api.github.com/repos/rfk/pyenchant/tags",
    "teams_url": "https://api.github.com/repos/rfk/pyenchant/teams",
    "trees_url": "https://api.github.com/repos/rfk/pyenchant/git/trees{/sha}",
    "updated_at": "2014-04-29T04:59:54Z",
    "url": "https://api.github.com/repos/rfk/pyenchant",
    "watchers": 54,
    "watchers_count": 54
}