{
    "archive_url": "https://api.github.com/repos/HubSpot/sanetime/{archive_format}{/ref}",
    "assignees_url": "https://api.github.com/repos/HubSpot/sanetime/assignees{/user}",
    "blobs_url": "https://api.github.com/repos/HubSpot/sanetime/git/blobs{/sha}",
    "branches_url": "https://api.github.com/repos/HubSpot/sanetime/branches{/branch}",
    "clone_url": "https://github.com/HubSpot/sanetime.git",
    "collaborators_url": "https://api.github.com/repos/HubSpot/sanetime/collaborators{/collaborator}",
    "comments_url": "https://api.github.com/repos/HubSpot/sanetime/comments{/number}",
    "commits_url": "https://api.github.com/repos/HubSpot/sanetime/commits{/sha}",
    "compare_url": "https://api.github.com/repos/HubSpot/sanetime/compare/{base}...{head}",
    "contents_url": "https://api.github.com/repos/HubSpot/sanetime/contents/{+path}",
    "contributors_url": "https://api.github.com/repos/HubSpot/sanetime/contributors",
    "created_at": "2011-10-14T13:56:56Z",
    "default_branch": "master",
    "description": "A sane date/time python interface #hubspot-open-source",
    "downloads_url": "https://api.github.com/repos/HubSpot/sanetime/downloads",
    "events_url": "https://api.github.com/repos/HubSpot/sanetime/events",
    "fork": false,
    "forks": 5,
    "forks_count": 5,
    "forks_url": "https://api.github.com/repos/HubSpot/sanetime/forks",
    "full_name": "HubSpot/sanetime",
    "git_commits_url": "https://api.github.com/repos/HubSpot/sanetime/git/commits{/sha}",
    "git_refs_url": "https://api.github.com/repos/HubSpot/sanetime/git/refs{/sha}",
    "git_tags_url": "https://api.github.com/repos/HubSpot/sanetime/git/tags{/sha}",
    "git_url": "git://github.com/HubSpot/sanetime.git",
    "has_downloads": true,
    "has_issues": true,
    "has_wiki": true,
    "homepage": "http://github.hubspot.com/sanetime",
    "hooks_url": "https://api.github.com/repos/HubSpot/sanetime/hooks",
    "html_url": "https://github.com/HubSpot/sanetime",
    "id": 2576448,
    "issue_comment_url": "https://api.github.com/repos/HubSpot/sanetime/issues/comments/{number}",
    "issue_events_url": "https://api.github.com/repos/HubSpot/sanetime/issues/events{/number}",
    "issues_url": "https://api.github.com/repos/HubSpot/sanetime/issues{/number}",
    "keys_url": "https://api.github.com/repos/HubSpot/sanetime/keys{/key_id}",
    "labels_url": "https://api.github.com/repos/HubSpot/sanetime/labels{/name}",
    "language": "Python",
    "languages_url": "https://api.github.com/repos/HubSpot/sanetime/languages",
    "merges_url": "https://api.github.com/repos/HubSpot/sanetime/merges",
    "milestones_url": "https://api.github.com/repos/HubSpot/sanetime/milestones{/number}",
    "mirror_url": null,
    "name": "sanetime",
    "notifications_url": "https://api.github.com/repos/HubSpot/sanetime/notifications{?since,all,participating}",
    "open_issues": 1,
    "open_issues_count": 1,
    "owner": {
        "avatar_url": "https://avatars.githubusercontent.com/u/326419?",
        "events_url": "https://api.github.com/users/HubSpot/events{/privacy}",
        "followers_url": "https://api.github.com/users/HubSpot/followers",
        "following_url": "https://api.github.com/users/HubSpot/following{/other_user}",
        "gists_url": "https://api.github.com/users/HubSpot/gists{/gist_id}",
        "gravatar_id": "f5ad5e85d9d130baa5c6bc673722b66f",
        "html_url": "https://github.com/HubSpot",
        "id": 326419,
        "login": "HubSpot",
        "organizations_url": "https://api.github.com/users/HubSpot/orgs",
        "received_events_url": "https://api.github.com/users/HubSpot/received_events",
        "repos_url": "https://api.github.com/users/HubSpot/repos",
        "site_admin": false,
        "starred_url": "https://api.github.com/users/HubSpot/starred{/owner}{/repo}",
        "subscriptions_url": "https://api.github.com/users/HubSpot/subscriptions",
        "type": "Organization",
        "url": "https://api.github.com/users/HubSpot"
    },
    "private": false,
    "pulls_url": "https://api.github.com/repos/HubSpot/sanetime/pulls{/number}",
    "pushed_at": "2013-12-01T23:35:51Z",
    "releases_url": "https://api.github.com/repos/HubSpot/sanetime/releases{/id}",
    "score": 1.0,
    "size": 1041,
    "ssh_url": "git@github.com:HubSpot/sanetime.git",
    "stargazers_count": 49,
    "stargazers_url": "https://api.github.com/repos/HubSpot/sanetime/stargazers",
    "statuses_url": "https://api.github.com/repos/HubSpot/sanetime/statuses/{sha}",
    "subscribers_url": "https://api.github.com/repos/HubSpot/sanetime/subscribers",
    "subscription_url": "https://api.github.com/repos/HubSpot/sanetime/subscription",
    "svn_url": "https://github.com/HubSpot/sanetime",
    "tags_url": "https://api.github.com/repos/HubSpot/sanetime/tags",
    "teams_url": "https://api.github.com/repos/HubSpot/sanetime/teams",
    "trees_url": "https://api.github.com/repos/HubSpot/sanetime/git/trees{/sha}",
    "updated_at": "2014-05-06T03:33:28Z",
    "url": "https://api.github.com/repos/HubSpot/sanetime",
    "watchers": 49,
    "watchers_count": 49
}