{
    "archive_url": "https://api.github.com/repos/nicoulaj/rainbow/{archive_format}{/ref}",
    "assignees_url": "https://api.github.com/repos/nicoulaj/rainbow/assignees{/user}",
    "blobs_url": "https://api.github.com/repos/nicoulaj/rainbow/git/blobs{/sha}",
    "branches_url": "https://api.github.com/repos/nicoulaj/rainbow/branches{/branch}",
    "clone_url": "https://github.com/nicoulaj/rainbow.git",
    "collaborators_url": "https://api.github.com/repos/nicoulaj/rainbow/collaborators{/collaborator}",
    "comments_url": "https://api.github.com/repos/nicoulaj/rainbow/comments{/number}",
    "commits_url": "https://api.github.com/repos/nicoulaj/rainbow/commits{/sha}",
    "compare_url": "https://api.github.com/repos/nicoulaj/rainbow/compare/{base}...{head}",
    "contents_url": "https://api.github.com/repos/nicoulaj/rainbow/contents/{+path}",
    "contributors_url": "https://api.github.com/repos/nicoulaj/rainbow/contributors",
    "created_at": "2011-11-19T20:33:07Z",
    "default_branch": "master",
    "description": "Colorize commands output or STDIN using patterns.",
    "downloads_url": "https://api.github.com/repos/nicoulaj/rainbow/downloads",
    "events_url": "https://api.github.com/repos/nicoulaj/rainbow/events",
    "fork": false,
    "forks": 11,
    "forks_count": 11,
    "forks_url": "https://api.github.com/repos/nicoulaj/rainbow/forks",
    "full_name": "nicoulaj/rainbow",
    "git_commits_url": "https://api.github.com/repos/nicoulaj/rainbow/git/commits{/sha}",
    "git_refs_url": "https://api.github.com/repos/nicoulaj/rainbow/git/refs{/sha}",
    "git_tags_url": "https://api.github.com/repos/nicoulaj/rainbow/git/tags{/sha}",
    "git_url": "git://github.com/nicoulaj/rainbow.git",
    "has_downloads": true,
    "has_issues": true,
    "has_wiki": false,
    "homepage": "",
    "hooks_url": "https://api.github.com/repos/nicoulaj/rainbow/hooks",
    "html_url": "https://github.com/nicoulaj/rainbow",
    "id": 2810646,
    "issue_comment_url": "https://api.github.com/repos/nicoulaj/rainbow/issues/comments/{number}",
    "issue_events_url": "https://api.github.com/repos/nicoulaj/rainbow/issues/events{/number}",
    "issues_url": "https://api.github.com/repos/nicoulaj/rainbow/issues{/number}",
    "keys_url": "https://api.github.com/repos/nicoulaj/rainbow/keys{/key_id}",
    "labels_url": "https://api.github.com/repos/nicoulaj/rainbow/labels{/name}",
    "language": "Python",
    "languages_url": "https://api.github.com/repos/nicoulaj/rainbow/languages",
    "merges_url": "https://api.github.com/repos/nicoulaj/rainbow/merges",
    "milestones_url": "https://api.github.com/repos/nicoulaj/rainbow/milestones{/number}",
    "mirror_url": null,
    "name": "rainbow",
    "notifications_url": "https://api.github.com/repos/nicoulaj/rainbow/notifications{?since,all,participating}",
    "open_issues": 15,
    "open_issues_count": 15,
    "owner": {
        "avatar_url": "https://avatars.githubusercontent.com/u/3162?",
        "events_url": "https://api.github.com/users/nicoulaj/events{/privacy}",
        "followers_url": "https://api.github.com/users/nicoulaj/followers",
        "following_url": "https://api.github.com/users/nicoulaj/following{/other_user}",
        "gists_url": "https://api.github.com/users/nicoulaj/gists{/gist_id}",
        "gravatar_id": "ea5e4a27d69f33ede64742e1c9708133",
        "html_url": "https://github.com/nicoulaj",
        "id": 3162,
        "login": "nicoulaj",
        "organizations_url": "https://api.github.com/users/nicoulaj/orgs",
        "received_events_url": "https://api.github.com/users/nicoulaj/received_events",
        "repos_url": "https://api.github.com/users/nicoulaj/repos",
        "site_admin": false,
        "starred_url": "https://api.github.com/users/nicoulaj/starred{/owner}{/repo}",
        "subscriptions_url": "https://api.github.com/users/nicoulaj/subscriptions",
        "type": "User",
        "url": "https://api.github.com/users/nicoulaj"
    },
    "private": false,
    "pulls_url": "https://api.github.com/repos/nicoulaj/rainbow/pulls{/number}",
    "pushed_at": "2012-08-01T10:19:03Z",
    "releases_url": "https://api.github.com/repos/nicoulaj/rainbow/releases{/id}",
    "score": 1.0,
    "size": 289,
    "ssh_url": "git@github.com:nicoulaj/rainbow.git",
    "stargazers_count": 41,
    "stargazers_url": "https://api.github.com/repos/nicoulaj/rainbow/stargazers",
    "statuses_url": "https://api.github.com/repos/nicoulaj/rainbow/statuses/{sha}",
    "subscribers_url": "https://api.github.com/repos/nicoulaj/rainbow/subscribers",
    "subscription_url": "https://api.github.com/repos/nicoulaj/rainbow/subscription",
    "svn_url": "https://github.com/nicoulaj/rainbow",
    "tags_url": "https://api.github.com/repos/nicoulaj/rainbow/tags",
    "teams_url": "https://api.github.com/repos/nicoulaj/rainbow/teams",
    "trees_url": "https://api.github.com/repos/nicoulaj/rainbow/git/trees{/sha}",
    "updated_at": "2014-05-02T11:50:41Z",
    "url": "https://api.github.com/repos/nicoulaj/rainbow",
    "watchers": 41,
    "watchers_count": 41
}